{
  "episode_id": "episode_20251129_214713_906256",
  "label": "WoodBlock_Red",
  "batch_progress": "78/80",
  "real_sampling_rate": 200.07047438285923,
  "num_samples": 2808,
  "duration_s": 14.035054440999374,
  "log_file": "/home/martina/Y3_Project/learn_PyBullet/outputs/logs/position_logs.json",
  "missed_segments": [
    1,
    5,
    6,
    7,
    8,
    9
  ],
  "joint_names": [
    "shoulder_pan",
    "shoulder_lift",
    "elbow_flex",
    "wrist_flex",
    "wrist_roll",
    "gripper"
  ]
}